<?xml version="1.0" encoding="utf-8" ?>
<c2layout>
    <name>Layout 1</name>
    <sid>839526504754713</sid>
    <event-sheet># common</event-sheet>
    <size>
        <width>1920</width>
        <height>432</height>
    </size>
    <margins>
        <horizontal>500</horizontal>
        <vertical>500</vertical>
    </margins>
    <unbounded-scrolling>0</unbounded-scrolling>
    <layers>
        <layer name="max parallax" sid="847317677865429">
            <initially-visible>1</initially-visible>
            <background-color>8,131,254</background-color>
            <transparent>0</transparent>
            <parallax>
                <x>1</x>
                <y>1</y>
            </parallax>
            <zoom-rate>1</zoom-rate>
            <opacity>1</opacity>
            <force-own-texture>0</force-own-texture>
            <global>0</global>
            <use-render-cells>0</use-render-cells>
            <blend-mode>0</blend-mode>
            <effect-fallback>0</effect-fallback>
            <instances />
            <effects />
        </layer>
        <layer name="background" sid="159004142693452">
            <initially-visible>1</initially-visible>
            <background-color>255,255,255</background-color>
            <transparent>1</transparent>
            <parallax>
                <x>1</x>
                <y>1</y>
            </parallax>
            <zoom-rate>1</zoom-rate>
            <opacity>1</opacity>
            <force-own-texture>0</force-own-texture>
            <global>0</global>
            <use-render-cells>0</use-render-cells>
            <blend-mode>0</blend-mode>
            <effect-fallback>0</effect-fallback>
            <instances>
                <instance type="tm_ground" uid="5">
                    <properties>
                        <initial-visibility>Visible</initial-visibility>
                        <tile-width>32</tile-width>
                        <tile-height>32</tile-height>
                        <tile-x-offset>0</tile-x-offset>
                        <tile-y-offset>0</tile-y-offset>
                        <tile-x-spacing>0</tile-x-spacing>
                        <tile-y-spacing>0</tile-y-spacing>
                        <seamless-mode>On</seamless-mode>
                    </properties>
                    <behavior-instances>
                        <behavior-instance type="Solid">
                            <properties>
                                <initial-state>Enabled</initial-state>
                            </properties>
                        </behavior-instance>
                        <behavior-instance type="Physics">
                            <properties>
                                <immovable>Yes</immovable>
                                <collision-mask>Use collision polygon</collision-mask>
                                <prevent-rotation>Yes</prevent-rotation>
                                <density>1</density>
                                <friction>0.5</friction>
                                <elasticity>0.2</elasticity>
                                <linear-damping>0</linear-damping>
                                <angular-damping>0.01</angular-damping>
                                <bullet>No</bullet>
                                <initial-state>Enabled</initial-state>
                            </properties>
                        </behavior-instance>
                    </behavior-instances>
                    <blend-mode>0</blend-mode>
                    <effect-fallback>0</effect-fallback>
                    <world>
                        <x>0</x>
                        <y>0</y>
                        <z>0</z>
                        <width>1920</width>
                        <height>448</height>
                        <depth>0</depth>
                        <hotspotX>0</hotspotX>
                        <hotspotY>0</hotspotY>
                        <opacity>1</opacity>
                    </world>
                    <tilemap-data>
                        <width>60</width>
                        <height>14</height>
                        <max-width>63</max-width>
                        <max-height>14</max-height>
                        <data>-1,-1,-1,-1,-1,-1,-1,-1,0,0,0,0,0,0,-1,-1,-1,-1,-1,-1,-1,-1,0,0,0,0,0,0,-1,-1,-1,-1,-1,-1,-1,-1,0,0,0,0,0,0,-1,-1,-1,-1,-1,-1,-1,-1,0,0,0,0,0,0,-1,-1,-1,-1,-1,-1,-1,-1,0,0,0,0,0,0,-1,-1,-1,-1,-1,-1,-1,-1,0,0,0,0,0,0,-1,-1,-1,-1,-1,-1,-1,-1,0,0,0,0,0,0,-1,-1,-1,-1,-1,-1,-1,-1,0,0,0,0,0,0,-1,-1,-1,-1,-1,-1,-1,-1,0,0,0,0,0,0,-1,-1,-1,-1,-1,-1,-1,-1,0,0,0,0,0,0,-1,-1,-1,-1,-1,-1,-1,-1,0,0,0,0,0,0,-1,-1,-1,-1,-1,-1,-1,-1,0,0,0,0,0,0,-1,-1,-1,-1,-1,-1,-1,-1,0,0,0,0,0,0,-1,-1,-1,-1,-1,-1,-1,-1,0,0,0,0,0,0,-1,-1,-1,-1,-1,-1,-1,-1,0,0,0,0,0,0,-1,-1,-1,-1,-1,-1,-1,-1,0,0,0,0,0,0,-1,-1,-1,-1,-1,-1,-1,-1,0,0,0,0,0,0,-1,-1,-1,-1,-1,-1,-1,-1,0,0,0,0,0,0,-1,-1,-1,-1,-1,-1,-1,-1,0,0,0,0,0,0,-1,-1,-1,-1,-1,-1,-1,-1,0,0,0,0,0,0,-1,-1,-1,-1,-1,-1,-1,-1,0,0,0,0,0,0,-1,-1,-1,-1,-1,-1,-1,-1,0,0,0,0,0,0,-1,-1,-1,-1,-1,-1,-1,-1,0,0,0,0,0,0,-1,-1,-1,-1,-1,-1,-1,-1,0,0,0,0,0,0,-1,-1,-1,-1,-1,-1,-1,-1,0,0,0,0,0,0,-1,-1,-1,-1,-1,-1,-1,-1,0,0,0,0,0,0,-1,-1,-1,-1,-1,-1,-1,-1,0,0,0,0,0,0,-1,-1,-1,-1,-1,-1,-1,-1,0,0,0,0,0,0,-1,-1,-1,-1,-1,-1,-1,-1,0,0,0,0,0,0,-1,-1,-1,-1,-1,-1,-1,-1,0,0,0,0,0,0,-1,-1,-1,-1,-1,-1,-1,-1,0,0,0,0,0,0,-1,-1,-1,-1,-1,-1,-1,-1,0,0,0,0,0,0,-1,-1,-1,-1,-1,-1,-1,-1,0,0,0,0,0,0,-1,-1,-1,-1,-1,-1,-1,-1,0,0,0,0,0,0,-1,-1,-1,-1,-1,-1,-1,-1,0,0,0,0,0,0,-1,-1,-1,-1,-1,-1,-1,-1,0,0,0,0,0,0,-1,-1,-1,-1,-1,-1,-1,-1,0,0,0,0,0,0,-1,-1,-1,-1,-1,-1,-1,-1,0,0,0,0,0,0,-1,-1,-1,-1,-1,-1,-1,-1,0,0,0,0,0,0,-1,-1,-1,-1,-1,-1,-1,-1,0,0,0,0,0,0,-1,-1,-1,-1,-1,-1,-1,-1,0,0,0,0,0,0,-1,-1,-1,-1,-1,-1,-1,-1,0,0,0,0,0,0,-1,-1,-1,-1,-1,-1,-1,-1,0,0,0,0,0,0,-1,-1,-1,-1,-1,-1,-1,-1,0,0,0,0,0,0,-1,-1,-1,-1,-1,-1,-1,-1,0,0,0,0,0,0,-1,-1,-1,-1,-1,-1,-1,-1,0,0,0,0,0,0,-1,-1,-1,-1,-1,-1,-1,-1,0,0,0,0,0,0,-1,-1,-1,-1,-1,-1,-1,-1,0,0,0,0,0,0,-1,-1,-1,-1,-1,-1,-1,-1,0,0,0,0,0,0,-1,-1,-1,-1,-1,-1,-1,-1,0,0,0,0,0,0,-1,-1,-1,-1,-1,-1,-1,-1,0,0,0,0,0,0,-1,-1,-1,-1,-1,-1,-1,-1,0,0,0,0,0,0,-1,-1,-1,-1,-1,-1,-1,-1,0,0,0,0,0,0,-1,-1,-1,-1,-1,-1,-1,-1,0,0,0,0,0,0,-1,-1,-1,-1,-1,-1,-1,-1,0,0,0,0,0,0,-1,-1,-1,-1,-1,-1,-1,-1,0,0,0,0,0,0,-1,-1,-1,-1,-1,-1,-1,-1,0,0,0,0,0,0,-1,-1,-1,-1,-1,-1,-1,-1,0,0,0,0,0,0,-1,-1,-1,-1,-1,-1,-1,-1,0,0,0,0,0,0,-1,-1,-1,-1,-1,-1,-1,-1,0,0,0,0,0,0,-1,-1,-1,-1,-1,-1,-1,-1,-1,-1,-1,-1,-1,-1,-1,-1,-1,-1,-1,-1,-1,-1,-1,-1,-1,-1,-1,-1,-1,-1,-1,-1,-1,-1,-1,-1,-1,-1,-1,-1,-1,-1</data>
                    </tilemap-data>
                </instance>
            </instances>
            <effects />
        </layer>
        <layer name="foreground" sid="348703002829625">
            <initially-visible>1</initially-visible>
            <background-color>255,255,255</background-color>
            <transparent>1</transparent>
            <parallax>
                <x>1</x>
                <y>1</y>
            </parallax>
            <zoom-rate>1</zoom-rate>
            <opacity>1</opacity>
            <force-own-texture>0</force-own-texture>
            <global>0</global>
            <use-render-cells>0</use-render-cells>
            <blend-mode>0</blend-mode>
            <effect-fallback>0</effect-fallback>
            <instances>
                <instance type="player1" uid="6">
                    <properties>
                        <initial-visibility>Visible</initial-visibility>
                        <initial-animation>Default</initial-animation>
                        <initial-frame>0</initial-frame>
                        <collisions>Enabled</collisions>
                    </properties>
                    <behavior-instances>
                        <behavior-instance type="ScrollTo">
                            <properties>
                                <initial-state>Enabled</initial-state>
                            </properties>
                        </behavior-instance>
                        <behavior-instance type="Physics">
                            <properties>
                                <immovable>No</immovable>
                                <collision-mask>Use collision polygon</collision-mask>
                                <prevent-rotation>No</prevent-rotation>
                                <density>1</density>
                                <friction>0.5</friction>
                                <elasticity>0.2</elasticity>
                                <linear-damping>0</linear-damping>
                                <angular-damping>0.01</angular-damping>
                                <bullet>No</bullet>
                                <initial-state>Enabled</initial-state>
                            </properties>
                        </behavior-instance>
                    </behavior-instances>
                    <blend-mode>0</blend-mode>
                    <effect-fallback>0</effect-fallback>
                    <world>
                        <x>96</x>
                        <y>224</y>
                        <z>0</z>
                        <width>-64</width>
                        <height>64</height>
                        <depth>0</depth>
                        <hotspotX>0.5</hotspotX>
                        <hotspotY>0.5</hotspotY>
                        <angle>0</angle>
                        <opacity>1</opacity>
                    </world>
                </instance>
                <instance type="player2" uid="7">
                    <properties>
                        <initial-visibility>Visible</initial-visibility>
                        <initial-animation>Default</initial-animation>
                        <initial-frame>0</initial-frame>
                        <collisions>Enabled</collisions>
                    </properties>
                    <behavior-instances>
                        <behavior-instance type="ScrollTo">
                            <properties>
                                <initial-state>Disabled</initial-state>
                            </properties>
                        </behavior-instance>
                        <behavior-instance type="Physics">
                            <properties>
                                <immovable>No</immovable>
                                <collision-mask>Use collision polygon</collision-mask>
                                <prevent-rotation>No</prevent-rotation>
                                <density>1</density>
                                <friction>0.5</friction>
                                <elasticity>0.2</elasticity>
                                <linear-damping>0</linear-damping>
                                <angular-damping>0.01</angular-damping>
                                <bullet>No</bullet>
                                <initial-state>Enabled</initial-state>
                            </properties>
                        </behavior-instance>
                    </behavior-instances>
                    <blend-mode>0</blend-mode>
                    <effect-fallback>0</effect-fallback>
                    <world>
                        <x>1824</x>
                        <y>224</y>
                        <z>0</z>
                        <width>64</width>
                        <height>64</height>
                        <depth>0</depth>
                        <hotspotX>0.5</hotspotX>
                        <hotspotY>0.5</hotspotY>
                        <angle>0</angle>
                        <opacity>1</opacity>
                    </world>
                </instance>
            </instances>
            <effects />
        </layer>
        <layer name="decals" sid="485649511668272">
            <initially-visible>1</initially-visible>
            <background-color>255,255,255</background-color>
            <transparent>1</transparent>
            <parallax>
                <x>1</x>
                <y>1</y>
            </parallax>
            <zoom-rate>1</zoom-rate>
            <opacity>1</opacity>
            <force-own-texture>0</force-own-texture>
            <global>0</global>
            <use-render-cells>0</use-render-cells>
            <blend-mode>0</blend-mode>
            <effect-fallback>0</effect-fallback>
            <instances />
            <effects />
        </layer>
        <layer name="light" sid="830771393461736">
            <initially-visible>1</initially-visible>
            <background-color>255,255,255</background-color>
            <transparent>1</transparent>
            <parallax>
                <x>1</x>
                <y>1</y>
            </parallax>
            <zoom-rate>1</zoom-rate>
            <opacity>1</opacity>
            <force-own-texture>0</force-own-texture>
            <global>0</global>
            <use-render-cells>0</use-render-cells>
            <blend-mode>0</blend-mode>
            <effect-fallback>0</effect-fallback>
            <instances />
            <effects />
        </layer>
        <layer name="interface" sid="287816820665611">
            <initially-visible>1</initially-visible>
            <background-color>255,255,255</background-color>
            <transparent>1</transparent>
            <parallax>
                <x>0</x>
                <y>0</y>
            </parallax>
            <zoom-rate>1</zoom-rate>
            <opacity>1</opacity>
            <force-own-texture>0</force-own-texture>
            <global>0</global>
            <use-render-cells>0</use-render-cells>
            <blend-mode>0</blend-mode>
            <effect-fallback>0</effect-fallback>
            <instances>
                <instance type="turn_timer" uid="4">
                    <properties>
                        <text></text>
                        <initial-visibility>Visible</initial-visibility>
                        <font>Comic Sans MS,-16,400,0</font>
                        <color>255,255,255</color>
                        <horizontal-alignment>Center</horizontal-alignment>
                        <vertical-alignment>Center</vertical-alignment>
                        <hotspot>Top-left</hotspot>
                        <wrapping>Word</wrapping>
                        <line-height>0</line-height>
                    </properties>
                    <blend-mode>0</blend-mode>
                    <effect-fallback>0</effect-fallback>
                    <world>
                        <x>288</x>
                        <y>32</y>
                        <z>0</z>
                        <width>192</width>
                        <height>32</height>
                        <depth>0</depth>
                        <hotspotX>0</hotspotX>
                        <hotspotY>0</hotspotY>
                        <angle>0</angle>
                        <opacity>1</opacity>
                    </world>
                </instance>
            </instances>
            <effects />
        </layer>
    </layers>
    <nonworld-instances>
        <instance type="XML" uid="3" />
    </nonworld-instances>
    <effects />
</c2layout>
